{
  "stock_id": "5347.TWO",
  "last_updated": "2025-12-04T15:14:40.569Z",
  "news": [
    {
      "Date": "2025-12-04",
      "Time": "23:14:40",
      "Source": "Gemini API",
      "Title": "[AI Summary] 無新聞可供分析",
      "URL": "",
      "Content": "在指定期間內沒有抓取到相關新聞。",
      "Language": "zh"
    },
    {
      "Date": "2025-12-04",
      "Time": "23:14:40",
      "Source": "Gemini API",
      "Title": "[AI Summary] No News Available for Analysis",
      "URL": "",
      "Content": "• No relevant news articles were fetched during the specified period.",
      "Language": "en"
    }
  ],
  "total_news_count": 2,
  "new_news_count": 0,
  "sources_summary": {
    "Yahoo": 0,
    "UDN": 0,
    "Liberty_Times": 0
  }
}